{
	"info": {
		"_postman_id": "98d5ec54-f774-4bbd-8a9a-42a6a1354c58",
		"name": "AuthTask",
		"schema": "https://schema.getpostman.com/json/collection/v2.1.0/collection.json",
		"_exporter_id": "50477584",
		"_collection_link": "https://vinodjayasudha-8835220.postman.co/workspace/e2da3122-5188-40e3-8e21-0bcb0c963c8e/collection/48630910-98d5ec54-f774-4bbd-8a9a-42a6a1354c58?action=share&source=collection_link&creator=50477584"
	},
	"item": [
		{
			"name": "register",
			"request": {
				"method": "POST",
				"header": [],
				"body": {
					"mode": "raw",
					"raw": "{\r\n  \"username\": \"vinoth\",\r\n  \"email\": \"vinoth001@example.com\",\r\n  \"password\": \"123456\",\r\n  \"role\": \"user\"\r\n}\r\n",
					"options": {
						"raw": {
							"language": "json"
						}
					}
				},
				"url": {
					"raw": "http://localhost:5000/api/users/register",
					"protocol": "http",
					"host": [
						"localhost"
					],
					"port": "5000",
					"path": [
						"api",
						"users",
						"register"
					]
				}
			},
			"response": []
		},
		{
			"name": "loginusers",
			"request": {
				"method": "POST",
				"header": [],
				"body": {
					"mode": "raw",
					"raw": "{\r\n  \"email\": \"vinoth001@example.com\",\r\n  \"password\": \"123456\"\r\n}\r\n\r\n\r\n",
					"options": {
						"raw": {
							"language": "json"
						}
					}
				},
				"url": {
					"raw": "http://localhost:5000/api/users/login",
					"protocol": "http",
					"host": [
						"localhost"
					],
					"port": "5000",
					"path": [
						"api",
						"users",
						"login"
					]
				}
			},
			"response": []
		},
		{
			"name": "getMe",
			"request": {
				"method": "GET",
				"header": [
					{
						"key": "Authorization",
						"value": "Bearer eyJhbGciOiJIUzI1NiIsInR5cCI6IkpXVCJ9.eyJpZCI6IjY5MzI2Yjk2ODE5NDJhMTc1NDE2NzMxMCIsImVtYWlsIjoidmlub3RoMDAxQGV4YW1wbGUuY29tIiwicm9sZSI6InVzZXIiLCJpYXQiOjE3NjQ5MTUyNTksImV4cCI6MTc2NDkxODg1OX0.GqKplkDFOGsZ281vv9nbhT4t390EL1X3CBdlRf-2aI0",
						"type": "text"
					}
				],
				"url": {
					"raw": "http://localhost:5000/api/users/me",
					"protocol": "http",
					"host": [
						"localhost"
					],
					"port": "5000",
					"path": [
						"api",
						"users",
						"me"
					]
				}
			},
			"response": []
		},
		{
			"name": "logoutusers",
			"request": {
				"method": "POST",
				"header": [
					{
						"key": "Authorization",
						"value": "Bearer eyJhbGciOiJIUzI1NiIsInR5cCI6IkpXVCJ9.eyJpZCI6IjY5MzI2Yjk2ODE5NDJhMTc1NDE2NzMxMCIsImVtYWlsIjoidmlub3RoMDAxQGV4YW1wbGUuY29tIiwicm9sZSI6InVzZXIiLCJpYXQiOjE3NjQ5MTUyNTksImV4cCI6MTc2NDkxODg1OX0.GqKplkDFOGsZ281vv9nbhT4t390EL1X3CBdlRf-2aI0",
						"type": "text"
					}
				],
				"url": {
					"raw": "http://localhost:5000/api/users/logout",
					"protocol": "http",
					"host": [
						"localhost"
					],
					"port": "5000",
					"path": [
						"api",
						"users",
						"logout"
					]
				}
			},
			"response": []
		}
	],
	"event": [
		{
			"listen": "prerequest",
			"script": {
				"type": "text/javascript",
				"packages": {},
				"requests": {},
				"exec": [
					""
				]
			}
		},
		{
			"listen": "test",
			"script": {
				"type": "text/javascript",
				"packages": {},
				"requests": {},
				"exec": [
					""
				]
			}
		}
	]
}